{
  "lastRunAt": "2026-06-24T06:35:09.523Z",
  "lastStatus": "ok",
  "lastAction": {
    "type": "single_article_publish",
    "slug": "lap-la-so-tu-vi-can-gi",
    "slugs": [
      "lap-la-so-tu-vi-can-gi"
    ],
    "reason": "Publish 1 people-first articles from SEMrush intent clusters; first topic: Người đọc muốn biết cần ngày giờ sinh nào trước khi lập lá số.",
    "approvalRequired": false,
    "allowedToCommitDeployAfterVerification": true
  },
  "lastKeywordSource": {
    "sourcePath": "D:\\DU AN CA NHAN WEBSITE\\tsh\\semrush_la_so_keywords.csv",
    "rowCount": 396,
    "warning": null
  },
  "lastSearchConsole": {
    "status": "skipped"
  },
  "lastDraftPaths": [
    "docs/seo-autopilot/drafts/lap-la-so-tu-vi-can-gi.md"
  ],
  "lastReportPath": "docs/seo-autopilot/reports/2026-06-24-weekly-content-batch.md",
  "nextVerificationCommands": [
    "npm run seo:autopilot",
    "npm test -- src/lib/content.test.ts src/lib/article-cover-assets.test.ts src/lib/seo-autopilot-core.test.ts",
    "npm run build"
  ]
}
