{
  "lastRunAt": "2026-07-18T01:31:35.904Z",
  "lastStatus": "ok",
  "lastPublishedSlug": "sao-liem-trinh",
  "lastPublishedAt": "2026-07-15T22:14:07.3485735Z",
  "lastAction": {
    "type": "single_article_publish",
    "slug": "sao-thien-phu",
    "slugs": [
      "sao-thien-phu"
    ],
    "reason": "Publish 1 people-first articles from SEMrush intent clusters; first topic: Nguoi doc muon hieu sao Thien Phu ve nang luc giu gin, quan tri tai nguyen va cach doc cung Tai Bach, Dien Trach, Phuc Duc.",
    "approvalRequired": false,
    "allowedToCommitDeployAfterVerification": true
  },
  "lastKeywordSource": {
    "sourcePath": "D:\\DU AN CA NHAN WEBSITE\\tsh\\semrush_la_so_keywords.csv",
    "rowCount": 396,
    "warning": null
  },
  "lastSearchConsole": {
    "status": "skipped"
  },
  "lastDraftPaths": [
    "docs/seo-autopilot/drafts/sao-thien-phu.md"
  ],
  "lastReportPath": "docs/seo-autopilot/reports/2026-07-18-weekly-content-batch.md",
  "nextVerificationCommands": [
    "npm run seo:autopilot",
    "npm test -- src/lib/content.test.ts src/lib/article-cover-assets.test.ts src/lib/seo-autopilot-core.test.ts",
    "npm run build"
  ]
}
